odoo/addons/product_supplier_code_purchase/README.rst
odoo/addons/product_supplier_code_purchase/__init__.py
odoo/addons/product_supplier_code_purchase/__manifest__.py
odoo/addons/product_supplier_code_purchase/i18n/de.po
odoo/addons/product_supplier_code_purchase/i18n/es.po
odoo/addons/product_supplier_code_purchase/i18n/es_MX.po
odoo/addons/product_supplier_code_purchase/i18n/fi.po
odoo/addons/product_supplier_code_purchase/i18n/fr.po
odoo/addons/product_supplier_code_purchase/i18n/it.po
odoo/addons/product_supplier_code_purchase/i18n/nl_NL.po
odoo/addons/product_supplier_code_purchase/i18n/product_supplier_code_purchase.pot
odoo/addons/product_supplier_code_purchase/i18n/pt_BR.po
odoo/addons/product_supplier_code_purchase/i18n/pt_PT.po
odoo/addons/product_supplier_code_purchase/i18n/ro.po
odoo/addons/product_supplier_code_purchase/i18n/sl.po
odoo/addons/product_supplier_code_purchase/models/__init__.py
odoo/addons/product_supplier_code_purchase/models/purchase_order.py
odoo/addons/product_supplier_code_purchase/readme/CONTRIBUTORS.rst
odoo/addons/product_supplier_code_purchase/readme/DESCRIPTION.rst
odoo/addons/product_supplier_code_purchase/readme/USAGE.rst
odoo/addons/product_supplier_code_purchase/static/description/icon.png
odoo/addons/product_supplier_code_purchase/static/description/index.html
odoo/addons/product_supplier_code_purchase/tests/__init__.py
odoo/addons/product_supplier_code_purchase/tests/test_product_supplier_code_purchase.py
odoo/addons/product_supplier_code_purchase/views/purchase_order_view.xml
odoo12_addon_product_supplier_code_purchase-12.0.1.0.0.99.dev13.dist-info/METADATA
odoo12_addon_product_supplier_code_purchase-12.0.1.0.0.99.dev13.dist-info/WHEEL
odoo12_addon_product_supplier_code_purchase-12.0.1.0.0.99.dev13.dist-info/top_level.txt
odoo12_addon_product_supplier_code_purchase-12.0.1.0.0.99.dev13.dist-info/RECORD
